ouroboros/__init__.py
ouroboros/main.py
ouroboros/ouroboros_functions.py
ouroboros/data/SHAP_feature_set.csv
ouroboros/data/__init__.py
ouroboros/data/all_genes_mouse_orthologs.csv
ouroboros/data/gene_order.csv
ouroboros/data/neurogen_example.h5ad
ouroboros/data/reference_embeddings.csv
ouroboros/data/train_matrix.csv
ouroboros/data/train_meta.csv
ouroboros/data/model/__init__.py
ouroboros/data/model/model.data-00000-of-00001
ouroboros/data/model/model.index
ouroboros/data/model/model.meta
ouroboros/scphere/__init__.py
ouroboros/scphere/distributions/__init__.py
ouroboros/scphere/distributions/hyperbolic_wrapped_norm.py
ouroboros/scphere/distributions/hyperspherical_uniform.py
ouroboros/scphere/distributions/von_mises_fisher.py
ouroboros/scphere/model/__init__.py
ouroboros/scphere/model/vae.py
ouroboros/scphere/model/vae_sp.py
ouroboros/scphere/ops/__init__.py
ouroboros/scphere/ops/ive.py
ouroboros/scphere/util/__init__.py
ouroboros/scphere/util/data.py
ouroboros/scphere/util/plot.py
ouroboros/scphere/util/trainer.py
ouroboros/scphere/util/trainer_sp.py
ouroboros/scphere/util/util.py
sc_ouroboros-1.0.4.dist-info/licenses/LICENSE
sc_ouroboros-1.0.4.dist-info/METADATA
sc_ouroboros-1.0.4.dist-info/WHEEL
sc_ouroboros-1.0.4.dist-info/entry_points.txt
sc_ouroboros-1.0.4.dist-info/top_level.txt
sc_ouroboros-1.0.4.dist-info/RECORD
