Metadata-Version: 2.4
Name: sc-ouroboros
Version: 1.0.4
Summary: A toolkit for investigating cell cycling dynamics in scRNA-seq
Author: Haley MacDonald
Author-email: Haley MacDonald <hmacdonald@bcgsc.ca>
License-Expression: MIT
Project-URL: Homepage, https://github.com/haleymac/Ouroboros
Requires-Python: <3.11,>=3.9
License-File: LICENSE
Requires-Dist: numpy<1.25,>=1.22
Requires-Dist: scipy<1.10,>=1.7
Requires-Dist: pandas>=0.21.0
Requires-Dist: anndata>=0.7.5
Requires-Dist: matplotlib>=3.1.0
Requires-Dist: seaborn>=0.11.2
Requires-Dist: scikit-learn>=0.24.2
Requires-Dist: plotly>=5.18.0
Requires-Dist: kaleido<1.0.0
Requires-Dist: nbformat
Requires-Dist: kneed
Requires-Dist: requests
Requires-Dist: tensorflow<2.12,>=2.8
Requires-Dist: tensorflow-probability<0.19,>=0.18
Dynamic: license-file
